{"alphabet": ["1", "e", "a", "c", "b", "0"], "states": ["0", "1", "2", "3", "4", "5", "6", "7", "8", "9", "10", "11", "12", "13"], "initial_states": ["4"], "accepting_states": ["11"], "transitions": [["0", "0", "1"], ["1", "1", "2"], ["2", "0", "3"], ["4", "e", "0"], ["3", "e", "5"], ["3", "e", "0"], ["4", "e", "5"], ["6", "a", "7"], ["8", "b", "9"], ["10", "e", "6"], ["10", "e", "8"], ["7", "e", "11"], ["9", "e", "11"], ["12", "c", "13"], ["10", "e", "12"], ["13", "e", "11"], ["5", "e", "10"]]}